si4pipeline/__init__.py
si4pipeline/abstract.py
si4pipeline/constructor.py
si4pipeline/entity.py
si4pipeline/feature_selection.py
si4pipeline/index_operation.py
si4pipeline/missing_imputation.py
si4pipeline/outlier_detection.py
si4pipeline/pipeline.py
si4pipeline-1.0.1.dist-info/METADATA
si4pipeline-1.0.1.dist-info/WHEEL
si4pipeline-1.0.1.dist-info/licenses/LICENSE.md
si4pipeline-1.0.1.dist-info/RECORD
