Metadata-Version: 2.3
Name: si4pipeline
Version: 1.0.1
Summary: Package for statistical test for data analysis pipeline by selective inference
Project-URL: repository, https://github.com/Takeuchi-Lab-SI-Group/si4pipeline
Author: Takeuchi Lab
Maintainer-email: Tomohiro Shiraishi <shirara1016@gmail.com>
Classifier: License :: OSI Approved :: MIT License
Classifier: Programming Language :: Python :: 3.10
Classifier: Programming Language :: Python :: 3.11
Classifier: Programming Language :: Python :: 3.12
Classifier: Programming Language :: Python :: 3.13
Requires-Python: >=3.10
Requires-Dist: numpy<2.0.0,>=1.26.4
Requires-Dist: scikit-learn>=1.5.1
Requires-Dist: sicore>=2.3.0
Requires-Dist: tqdm>=4.66.5
